{
  "services": {
    "ms-commands": {
      "apiName": "ms-commands",
      "protocol": "http",
      "host": "localhost",
      "port": 3001,
      "url": "http://localhost:3001/",
      "nonAuth": []
    },
    "ms-deliveries": {
      "apiName": "ms-deliveries",
      "protocol": "http",
      "host": "http://localhost",
      "port": 3002,
      "url": "http://localhost:3002/",
      "nonAuth": []
    },
    "ms-irttrackings": {
      "apiName": "ms-irttrackings",
      "protocol": "http",
      "host": "http://localhost",
      "port": 3003,
      "url": "http://localhost:3003/",
      "nonAuth": []
    },
    "ms-logs": {
      "apiName": "ms-logs",
      "protocol": "http",
      "host": "http://localhost",
      "port": 3004,
      "url": "http://localhost:3004/",
      "nonAuth": []
    },
    "ms-paiments": {
      "apiName": "ms-paiments",
      "protocol": "http",
      "host": "http://localhost",
      "port": 3005,
      "url": "http://localhost:3005/",
      "nonAuth": []
    },
    "ms-products": {
      "apiName": "ms-products",
      "protocol": "http",
      "host": "http://localhost",
      "port": 3006,
      "url": "http://localhost:3006/",
      "nonAuth": ["menu", "menus", "article", "articles"]
    },
    "stats": {
      "apiName": "ms-stats",
      "protocol": "http",
      "host": "http://localhost",
      "port": 3007,
      "url": "http://localhost:3007/",
      "nonAuth": []
    },
    "ms-users": {
      "apiName": "ms-users",
      "protocol": "http",
      "host": "http://localhost",
      "port": 3008,
      "url": "http://localhost:3008/",
      "nonAuth": ["authenticate", "create", "restaurants"]
    }
  }
}
